[{"id":0,"poslednjaPlacenaClanarina":"2019-07-08","ime":"Ivanca","prezime":"Milkov","godinaRodenja":1994,"telefom":"062781177","adresa":"Zorza Klemansoa 17","email":"sreckoradostan@gmail.com"},{"id":1,"poslednjaPlacenaClanarina":"2019-08-28","ime":"Dovla","prezime":"Lazic","godinaRodenja":1994,"telefom":"124124","adresa":"Krnjaca 25","email":"dovla@peder.com"},{"id":2,"poslednjaPlacenaClanarina":"2019-07-08","ime":"Steva","prezime":"Stevic","godinaRodenja":1994,"telefom":"141254","adresa":"Viser 1","email":"stevko@gmail.com"},{"id":3,"poslednjaPlacenaClanarina":"2019-08-28","ime":"Borivoje","prezime":"Macic","godinaRodenja":1910,"telefom":"123","adresa":"Beograd","email":"macic@gmail.com"},{"id":4,"poslednjaPlacenaClanarina":"2019-07-14","ime":"Dijana","prezime":"Braun","godinaRodenja":1959,"telefom":"31321312","adresa":"Zorza Klemansoa 17","email":"dijanabraun@gmail.com"},{"id":6,"poslednjaPlacenaClanarina":"2019-07-07","ime":"Miric","prezime":"Mirko","godinaRodenja":1992,"telefom":"062563763","adresa":"Mirkova 9 ","email":"mirkosrecan@gmail.com"},{"id":7,"poslednjaPlacenaClanarina":"2019-07-07","ime":"Mirko","prezime":"Canic","godinaRodenja":1992,"telefom":"3213123213","adresa":"","email":"Mirkic 2"},{"id":8,"poslednjaPlacenaClanarina":"2019-08-28","ime":"Toma","prezime":"Tomic","godinaRodenja":1992,"telefom":"1231212","adresa":"Tomicina 3","email":"tomicahappy@gmail.com"}]